macrorecorder/__init__.py
macrorecorder/__main__.py
macrorecorder/core/__init__.py
macrorecorder/core/config.py
macrorecorder/core/recorder.py
macrorecorder/core/storage.py
macrorecorder/gui/__init__.py
macrorecorder/gui/application.py
simple_macrorecorder-1.0.4.dist-info/METADATA
simple_macrorecorder-1.0.4.dist-info/WHEEL
simple_macrorecorder-1.0.4.dist-info/entry_points.txt
simple_macrorecorder-1.0.4.dist-info/licenses/LICENSE
simple_macrorecorder-1.0.4.dist-info/RECORD
