Metadata-Version: 2.4
Name: simple_macrorecorder
Version: 1.0.4
Summary: Simple macro recorder for keystrokes across operating systems
Project-URL: Homepage, https://github.com/werzum/MacroRecorder
License-Expression: GPL-3.0-or-later
License-File: LICENSE
Keywords: automation,keystrokes,macro,recorder
Requires-Python: >=3.10
Requires-Dist: platformdirs>=4.0.0
Requires-Dist: pynput>=1.8.1
Requires-Dist: pyside6>=6.6.0
